<?xml version="1.0" encoding="utf-8"?>
<MPCDI profile="3d" geometry="2" color="4" date="2020-04-22 17:39:10" version="2.0" >
  <display>
    <buffer id="__0006_10.0.10.22" >
      <region id="Display0" x="0" y="0" xSize="1" ySize="1" xResolution ="2560" yResolution="1600" >
        <frustum>
			<yaw>31.0000000</yaw>
			<pitch>15.0000000</pitch>
			<roll>15.0000000</roll>
			<rightAngle>53.0000000</rightAngle>
			<leftAngle>53.0000000</leftAngle>
			<upAngle>40.0000000</upAngle>
			<downAngle>40.0000000</downAngle>
        </frustum>
        <color>
          <decode type="gamma" gamma="1.0" />
          <encode type="gamma" gamma="1.0" />
        </color>
      </region>
    </buffer>
  </display>
  <files>
    <fileset region="Display0">
      <geometryWarpFile>
        <path>Display0.pfm</path>
        <interpolation>smooth</interpolation>
      </geometryWarpFile>
      <alphaMap>
        <path>Display0.png</path>
        <bitDepth>16</bitDepth>
        <componentDepth>3</componentDepth>
        <gammaEmbedded>1.0</gammaEmbedded>
      </alphaMap>
    </fileset>
  </files>
</MPCDI>
